PySimpleInput/__init__.py
PySimpleInput/__version__.py
PySimpleInput/inputter.py
PySimpleInput-0.0.6.5.dist-info/LICENSE
PySimpleInput-0.0.6.5.dist-info/METADATA
PySimpleInput-0.0.6.5.dist-info/WHEEL
PySimpleInput-0.0.6.5.dist-info/top_level.txt
PySimpleInput-0.0.6.5.dist-info/RECORD
