Metadata-Version: 2.1
Name: PySimpleInput
Version: 0.0.6.5
Summary: Advanced Input System
Home-page: https://github.com/turtleion/PySimpleInput
Author: Turtleion
Author-email: Turtleion <remastred89@gmail.com>
License: MIT
Project-URL: Homepage, https://github.com/turtleion/PySimpleInput
Project-URL: Bug Tracker, https://github.com/turtleion/PySimpleInput/issues
Keywords: Python3 Input
Classifier: Programming Language :: Python :: 3
Classifier: License :: OSI Approved :: MIT License
Classifier: Operating System :: OS Independent
Requires-Python: >=3.8
License-File: LICENSE
